[
    {
        "id" : 1,
        "hex" : "ff3b30",
    },
    {
        "id" : 2,
        "hex" : "ff9500",
    },
    {
        "id" : 3,
        "hex" : "ffcc00",
    },
    {
        "id" : 4,
        "hex" : "34c759",
    },
    {
        "id" : 5,
        "hex" : "5ac8fa",
    },
    {
        "id" : 6,
        "hex" : "007aff",
    },
    {
        "id" : 7,
        "hex" : "5856d6",
    },
    {
        "id" : 8,
        "hex" : "af52de",
    },
    {
        "id" : 9,
        "hex" : "ff2d55",
    },
    {
        "id" : 10,
        "hex" : "8e8e93",
    },
]
